Release/filter.cp39-win_amd64.pyd
cnkalman/__init__.py
cnkalman/codegen.py
cnkalman-0.1.14.dist-info/LICENSE
cnkalman-0.1.14.dist-info/METADATA
cnkalman-0.1.14.dist-info/WHEEL
cnkalman-0.1.14.dist-info/top_level.txt
cnkalman-0.1.14.dist-info/RECORD
