Metadata-Version: 2.1
Name: cnkalman
Version: 0.1.14
Summary: Support tools for cnkalman
Author: Justin Berger
Author-email: jdavidberger@gmail.com
Classifier: Programming Language :: Python :: 3
Classifier: Operating System :: OS Independent
Requires-Python: >=3.6
License-File: LICENSE
Requires-Dist: sympy
Requires-Dist: symengine
Requires-Dist: cmake
